PeptideBuilder/Geometry.py
PeptideBuilder/PeptideBuilder.py
PeptideBuilder/__init__.py
PeptideBuilder-1.1.0.dist-info/LICENSE.txt
PeptideBuilder-1.1.0.dist-info/METADATA
PeptideBuilder-1.1.0.dist-info/WHEEL
PeptideBuilder-1.1.0.dist-info/top_level.txt
PeptideBuilder-1.1.0.dist-info/RECORD
