Metadata-Version: 2.1
Name: PeptideBuilder
Version: 1.1.0
Summary: Create peptide PDB files with specified geometry
Home-page: https://github.com/clauswilke/PeptideBuilder
Author: Matthew Z. Tien
Author-email: Matthew.Tien89@gmail.com
License: UNKNOWN
Download-URL: https://github.com/clauswilke/PeptideBuilder/releases
Platform: Tested on Mac OS X and Windows 10
Classifier: Development Status :: 5 - Production/Stable
Classifier: License :: OSI Approved :: MIT License
Classifier: Programming Language :: Python
Classifier: Programming Language :: Python :: 3
Classifier: Topic :: Scientific/Engineering :: Bio-Informatics
Classifier: Topic :: Scientific/Engineering :: Chemistry
Classifier: Intended Audience :: Science/Research
Requires-Dist: Biopython
Provides-Extra: test
Requires-Dist: pytest ; extra == 'test'
Requires-Dist: coverage ; extra == 'test'
Requires-Dist: pytest-cov ; extra == 'test'
Requires-Dist: collective.checkdocs ; extra == 'test'
Requires-Dist: pygments ; extra == 'test'
Requires-Dist: Biopython ; extra == 'test'
